gcloud_secret_configure/__init__.py
gcloud_secret_configure/config.py
gcloud_secret_configure/secret.py
tests/__init__.py
tests/test_config_get.py
tests/test_config_integration.py
tests/test_config_parse.py
tests/test_config_repository.py
tests/test_secret.py
gcloud_secret_configure-1.0.1.dist-info/LICENSE
gcloud_secret_configure-1.0.1.dist-info/METADATA
gcloud_secret_configure-1.0.1.dist-info/WHEEL
gcloud_secret_configure-1.0.1.dist-info/top_level.txt
gcloud_secret_configure-1.0.1.dist-info/RECORD
